MANIFEST.in
README.rst
dpc-single
setup.py
dpc/__init__.py
dpc/argp.py
dpc/boxes.py
dpc/events.py
dpc/log.py
dpc/pics.py
dpc/single.py
dpc.egg-info/PKG-INFO
dpc.egg-info/SOURCES.txt
dpc.egg-info/dependency_links.txt
dpc.egg-info/not-zip-safe
dpc.egg-info/top_level.txt
dpc/fonts/Roboto/Apache License.txt
dpc/fonts/Roboto/Roboto-Black.ttf
dpc/fonts/Roboto/Roboto-BlackItalic.ttf
dpc/fonts/Roboto/Roboto-Bold.ttf
dpc/fonts/Roboto/Roboto-BoldItalic.ttf
dpc/fonts/Roboto/Roboto-Italic.ttf
dpc/fonts/Roboto/Roboto-Light.ttf
dpc/fonts/Roboto/Roboto-LightItalic.ttf
dpc/fonts/Roboto/Roboto-Medium.ttf
dpc/fonts/Roboto/Roboto-MediumItalic.ttf
dpc/fonts/Roboto/Roboto-Regular.ttf
dpc/fonts/Roboto/Roboto-Thin.ttf
dpc/fonts/Roboto/Roboto-ThinItalic.ttf
dpc/fonts/Roboto/RobotoCondensed-Bold.ttf
dpc/fonts/Roboto/RobotoCondensed-BoldItalic.ttf
dpc/fonts/Roboto/RobotoCondensed-Italic.ttf
dpc/fonts/Roboto/RobotoCondensed-Light.ttf
dpc/fonts/Roboto/RobotoCondensed-LightItalic.ttf
dpc/fonts/Roboto/RobotoCondensed-Regular.ttf