Metadata-Version: 1.1
Name: dpc
Version: 0.1
Summary: Daily photo calendar
Home-page: https://github.com/svalgaard/daily-photo-calendar
Author: Jens Svalgaard Kohrt
Author-email: python@svalgaard.net
License: MIT
Platform: UNKNOWN
Classifier: Development Status :: 4 - Beta
Classifier: Intended Audience :: End Users/Desktop
Classifier: Programming Language :: Python :: 3
Classifier: License :: OSI Approved :: MIT License
Requires: Pillow
